pidgin/__init__.ipynb
pidgin/__init__.py
pidgin/_version.py
pidgin/config.ipynb
pidgin/config.py
pidgin/conventions.ipynb
pidgin/disp.ipynb
pidgin/markdown.ipynb
pidgin/recall.ipynb
pidgin/template.ipynb
pidgin-0.0.1.dist-info/METADATA
pidgin-0.0.1.dist-info/RECORD
pidgin-0.0.1.dist-info/WHEEL
pidgin-0.0.1.dist-info/top_level.txt
