Metadata-Version: 2.1
Name: pidgin
Version: 0.0.1
Summary: Conventions for writing code in the notebook.
Home-page: https://github.com/deathbeds/pidgin
Author: deathbeds
Author-email: tony.fast@gmail.com
License: BSD-3-Clause
Platform: UNKNOWN
Classifier: Development Status :: 4 - Beta
Classifier: Framework :: IPython
Classifier: Framework :: Jupyter
Classifier: Intended Audience :: Developers
Classifier: Natural Language :: English
Classifier: License :: OSI Approved :: BSD License
Classifier: Programming Language :: Python
Classifier: Programming Language :: Python :: 3.6
Requires-Python: >=3.6
Requires-Dist: dataclasses
Requires-Dist: CommonMark
Requires-Dist: pyyaml
Requires-Dist: ipython
Requires-Dist: nbconvert
Requires-Dist: hypothesis
Requires-Dist: graphviz
Requires-Dist: importnb
